gitoptim/__init__.py
gitoptim/__main__.py
gitoptim/commands/__init__.py
gitoptim/commands/analyse/__init__.py
gitoptim/commands/analyse/logs.py
gitoptim/commands/analyse/main.py
gitoptim/commands/memlab.py
gitoptim/commands/tag.py
gitoptim/main.py
gitoptim/schemas/__init__.py
gitoptim/schemas/workflows.py
gitoptim/services/__init__.py
gitoptim/services/gitlab.py
gitoptim/utils/__init__.py
gitoptim/utils/cli.py
gitoptim/utils/environment.py
gitoptim/utils/tag.py
gitoptim-0.1.24.dist-info/METADATA
gitoptim-0.1.24.dist-info/WHEEL
gitoptim-0.1.24.dist-info/entry_points.txt
gitoptim-0.1.24.dist-info/RECORD
