Metadata-Version: 2.1
Name: gitoptim
Version: 0.1.24
Summary: SDK tool to connect Gitlab pipelines with Workflows
Author: Łukasz Leszko
Author-email: leszko.lucas@gmail.com
Requires-Python: >=3.11,<4.0
Classifier: Programming Language :: Python :: 3
Classifier: Programming Language :: Python :: 3.11
Classifier: Programming Language :: Python :: 3.12
Requires-Dist: httpx (>=0.27.0,<0.28.0)
Requires-Dist: pydantic (>=2.6.3,<3.0.0)
Requires-Dist: typer[all] (>=0.9.0,<0.10.0)
